herbs/__init__.py
herbs/about_herbs.py
herbs/allen_downloader.py
herbs/atlas_downloader.py
herbs/atlas_loader.py
herbs/atlas_processor.py
herbs/atlas_view.py
herbs/czi_reader.py
herbs/herbsgui.py
herbs/image_curves.py
herbs/image_reader.py
herbs/image_stacks.py
herbs/image_view.py
herbs/images_reader.py
herbs/label_tree.py
herbs/layers_control.py
herbs/main_window.ui
herbs/movable_points.py
herbs/obj_items.py
herbs/object_control.py
herbs/popup_message.py
herbs/probe_utiles.py
herbs/run_herbs.py
herbs/slice_stacks.py
herbs/toolbox.py
herbs/triangulation_points.py
herbs/uuuuuu.py
herbs/version.py
herbs/widgets_utils.py
herbs/wtiles.py
herbs/data/atlas_labels.pkl
herbs/data/query.csv
herbs/icons/backward.svg
herbs/icons/dot.svg
herbs/icons/down-arrow.svg
herbs/icons/fast_backward.svg
herbs/icons/fast_forward.svg
herbs/icons/forward.svg
herbs/icons/object.svg
herbs/icons/tdown.svg
herbs/icons/tree_close.svg
herbs/icons/tree_open.svg
herbs/icons/up-arrow.svg
herbs/icons/layers/add.png
herbs/icons/layers/ai.png
herbs/icons/layers/eye_off.png
herbs/icons/layers/eye_on.png
herbs/icons/layers/eye_white.png
herbs/icons/layers/hi.png
herbs/icons/layers/trash.png
herbs/icons/sidebar/add.png
herbs/icons/sidebar/atlascontrol.png
herbs/icons/sidebar/atlascontrol.svg
herbs/icons/sidebar/bnd.svg
herbs/icons/sidebar/c_section.png
herbs/icons/sidebar/c_section2.png
herbs/icons/sidebar/cell.svg
herbs/icons/sidebar/check.svg
herbs/icons/sidebar/compare.svg
herbs/icons/sidebar/contour.svg
herbs/icons/sidebar/h_section.png
herbs/icons/sidebar/info.svg
herbs/icons/sidebar/layers.png
herbs/icons/sidebar/layers.svg
herbs/icons/sidebar/line.svg
herbs/icons/sidebar/link.svg
herbs/icons/sidebar/link_off.svg
herbs/icons/sidebar/merge.svg
herbs/icons/sidebar/object.svg
herbs/icons/sidebar/probe.png
herbs/icons/sidebar/probe.svg
herbs/icons/sidebar/rotation_horizontal.svg
herbs/icons/sidebar/rotation_vertical.svg
herbs/icons/sidebar/s_section.png
herbs/icons/sidebar/tool.png
herbs-0.2.8.dist-info/LICENSE.txt
herbs-0.2.8.dist-info/METADATA
herbs-0.2.8.dist-info/WHEEL
herbs-0.2.8.dist-info/top_level.txt
herbs-0.2.8.dist-info/RECORD
