Metadata-Version: 2.1
Name: herbs
Version: 0.2.8
Summary: A Python-based GUI for Histological E-data Registration in Brain Space
Home-page: https://github.com/JingyiGF/HERBS
Author: Jingyi GF
Author-email: jingyi.g.fuglstad@gmail.com
Project-URL: Bug Tracker, https://github.com/JingyiGF/HERBS/issues
Keywords: brain atlas,histological image registration,probe coordinates
Classifier: Development Status :: 3 - Alpha
Classifier: Intended Audience :: Science/Research
Classifier: Intended Audience :: Developers
Classifier: Intended Audience :: Education
Classifier: License :: OSI Approved :: MIT License
Classifier: Programming Language :: Python :: 3
Classifier: Programming Language :: Python :: 3.8
Classifier: Programming Language :: Python :: 3.9
Classifier: Programming Language :: Python :: 3.10
Classifier: Programming Language :: Python :: 3 :: Only
Classifier: Topic :: Software Development
Classifier: Topic :: Scientific/Engineering
Classifier: Typing :: Typed
Classifier: Operating System :: Microsoft :: Windows
Classifier: Operating System :: POSIX
Classifier: Operating System :: Unix
Classifier: Operating System :: MacOS
Requires-Python: >=3.8
License-File: LICENSE.txt
Requires-Dist: aicspylibczi >=3.0.3
Requires-Dist: pyqtgraph ==0.12.3
Requires-Dist: PyOpenGL >=3.1.5
Requires-Dist: QtRangeSlider ==0.1.5
Requires-Dist: opencv-python >=4.5.4.60
Requires-Dist: numba >=0.54.1
Requires-Dist: numpy >=1.20.3
Requires-Dist: scipy >=1.7.3
Requires-Dist: requests >=2.26.0
Requires-Dist: nibabel >=3.2.1
Requires-Dist: pynrrd >=0.4.3
Requires-Dist: tifffile >=2021.11.2
Requires-Dist: pandas >=1.3.5
Requires-Dist: natsort >=8.0.2
Requires-Dist: imagecodecs >=2022.2.22
Requires-Dist: h5py >=3.7.0
Requires-Dist: tables >=3.7.0
Requires-Dist: PyQt5 >=5.15.5 ; python_version == "3.10"
Requires-Dist: PyQt5 >=5.14.2 ; python_version == "3.8"
Requires-Dist: PyQt5 >=5.15.1 ; python_version == "3.9"
